{
  "kind": "singleType",
  "collectionName": "resumes",
  "info": {
    "singularName": "resume",
    "pluralName": "resumes",
    "displayName": "resume",
    "description": ""
  },
  "options": {
    "draftAndPublish": true
  },
  "pluginOptions": {
    "i18n": {
      "localized": true
    }
  },
  "attributes": {
    "headline": {
      "type": "string",
      "pluginOptions": {
        "i18n": {
          "localized": true
        }
      }
    },
    "location": {
      "type": "string",
      "default": "San jose, Costa Rica",
      "pluginOptions": {
        "i18n": {
          "localized": true
        }
      }
    },
    "email_label": {
      "type": "string",
      "default": "jgatjens@gmail.com",
      "pluginOptions": {
        "i18n": {
          "localized": true
        }
      }
    },
    "email": {
      "type": "string",
      "pluginOptions": {
        "i18n": {
          "localized": true
        }
      }
    },
    "summary_label": {
      "type": "string",
      "pluginOptions": {
        "i18n": {
          "localized": true
        }
      }
    },
    "summary": {
      "type": "richtext",
      "pluginOptions": {
        "i18n": {
          "localized": true
        }
      }
    },
    "skill_label": {
      "type": "string",
      "pluginOptions": {
        "i18n": {
          "localized": true
        }
      }
    },
    "skills": {
      "type": "richtext",
      "pluginOptions": {
        "i18n": {
          "localized": true
        }
      }
    },
    "work_label": {
      "type": "string",
      "pluginOptions": {
        "i18n": {
          "localized": true
        }
      }
    },
    "history": {
      "type": "component",
      "repeatable": true,
      "component": "shared.experience",
      "pluginOptions": {
        "i18n": {
          "localized": true
        }
      }
    },
    "academic_label": {
      "type": "string",
      "pluginOptions": {
        "i18n": {
          "localized": true
        }
      }
    },
    "open_graph": {
      "type": "component",
      "repeatable": false,
      "component": "shared.opengraph",
      "pluginOptions": {
        "i18n": {
          "localized": true
        }
      }
    }
  }
}
